notifyker/__init__.py
notifyker/chainer/__init__.py
notifyker/chainer/extensions_tg_notifier.py
notifyker/keras/__init__.py
notifyker/keras/callback_base.py
notifyker/keras/callback_simple.py
notifyker/notifiers/__init__.py
notifyker/notifiers/notifier_base.py
notifyker/notifiers/notifier_telegram.py
notifyker/notifiers/notifier_telegram_menu.py
notifyker-2.0.3.dist-info/LICENSE
notifyker-2.0.3.dist-info/METADATA
notifyker-2.0.3.dist-info/WHEEL
notifyker-2.0.3.dist-info/top_level.txt
notifyker-2.0.3.dist-info/RECORD
