Metadata-Version: 2.1
Name: notifyker
Version: 2.0.3
Summary: Notifications for ML libraries (Keras, Chainer) using telegram bot
Home-page: https://github.com/qwinpin/notifyker
Author: Timur Sokhin
Author-email: qwinpin@gmail.com
License: UNKNOWN
Keywords: notifyker chainer keras telegram bot notification callback extentions
Platform: UNKNOWN
Classifier: Programming Language :: Python :: 3
Classifier: License :: OSI Approved :: MIT License
Classifier: Operating System :: OS Independent
